bpx/__init__.py
bpx/account.py
bpx/async_/__init__.py
bpx/async_/account.py
bpx/async_/public.py
bpx/base/__init__.py
bpx/base/base_account.py
bpx/base/base_public.py
bpx/constants/__init__.py
bpx/constants/enums.py
bpx/exceptions/__init__.py
bpx/http_client/__init__.py
bpx/http_client/async_http_client.py
bpx/http_client/base/__init__.py
bpx/http_client/base/http_client.py
bpx/http_client/sync_http_client.py
bpx/models/__init__.py
bpx/models/objects.py
bpx/public.py
bpx_py-2.0.10.dist-info/LICENSE
bpx_py-2.0.10.dist-info/METADATA
bpx_py-2.0.10.dist-info/WHEEL
bpx_py-2.0.10.dist-info/RECORD
